pygamelib/__init__.py
pygamelib/actuators.py
pygamelib/base.py
pygamelib/board_items.py
pygamelib/constants.py
pygamelib/engine-threaded.py
pygamelib/engine.py
pygamelib/functions.py
pygamelib/assets/__init__.py
pygamelib/assets/graphics.py
pygamelib/assets/fonts/__init__.py
pygamelib/assets/fonts/8bits/__init__.py
pygamelib/assets/fonts/figlet-mirror/__init__.py
pygamelib/assets/fonts/figlet-pepper/__init__.py
pygamelib/assets/fonts/figlet-rounded/__init__.py
pygamelib/assets/fonts/figlet-univers/__init__.py
pygamelib/assets/fonts/figlet-wavy/__init__.py
pygamelib/gfx/__init__.py
pygamelib/gfx/core.py
pygamelib/gfx/particles.py
pygamelib/gfx/ui.py
pygamelib-1.3.0.data/scripts/pgl-board-tester.py
pygamelib-1.3.0.data/scripts/pgl-editor.py
pygamelib-1.3.0.data/scripts/pgl-sprite-editor.py
pygamelib-1.3.0.dist-info/LICENSE
pygamelib-1.3.0.dist-info/METADATA
pygamelib-1.3.0.dist-info/WHEEL
pygamelib-1.3.0.dist-info/top_level.txt
pygamelib-1.3.0.dist-info/RECORD
