Metadata-Version: 2.1
Name: pygamelib
Version: 1.3.0
Summary: A (not so) small library for terminal based game development.
Home-page: https://www.pygamelib.org
Author: Arnaud Dupuis
Author-email: 8bitscoding@gmail.com
Project-URL: Documentation, https://pygamelib.readthedocs.io/en/latest/index.html
Project-URL: Source, https://github.com/pygamelib/pygamelib
Project-URL: Tracker, https://github.com/pygamelib/pygamelib/issues
Project-URL: Wiki, https://github.com/pygamelib/pygamelib/wiki
Project-URL: Tech blog, https://8bitscoding.io/
Keywords: game,development,beginner,console,terminal
Classifier: Programming Language :: Python :: 3
Classifier: Programming Language :: Python :: 3.6
Classifier: Programming Language :: Python :: 3.7
Classifier: Programming Language :: Python :: 3.8
Classifier: Programming Language :: Python :: 3.9
Classifier: Programming Language :: Python :: 3.10
Classifier: Development Status :: 4 - Beta
Classifier: Environment :: Console
Classifier: Topic :: Terminals
Classifier: License :: OSI Approved :: GNU General Public License v3 (GPLv3)
Classifier: Operating System :: OS Independent
Requires-Python: >=3.6
License-File: LICENSE
